setup.py
Pandas3.egg-info/PKG-INFO
Pandas3.egg-info/SOURCES.txt
Pandas3.egg-info/dependency_links.txt
Pandas3.egg-info/requires.txt
Pandas3.egg-info/top_level.txt
pandas3/__init__.py
pandas3/utils.py