Metadata-Version: 1.0
Name: Pandas3
Version: 0.0.1
Summary:  Boto3 extension to help facilitate data science workflows with S3 and Pandas
Home-page: UNKNOWN
Author: Spencer Porter
Author-email: spencer.porter3@gmail.com
License: http://www.apache.org/licenses/LICENSE-2.0
Keywords: aws,s3,pandas,boto3
Platform: UNKNOWN
